dmvimlemfodfTest/BMI_test.py
dmvimlemfodfTest/test1.py
dmvimlemfodfTest/test2.py
dmvimlemfodfTest-0.0.0.2.dist-info/METADATA
dmvimlemfodfTest-0.0.0.2.dist-info/WHEEL
dmvimlemfodfTest-0.0.0.2.dist-info/top_level.txt
dmvimlemfodfTest-0.0.0.2.dist-info/RECORD
